fondat/annotation.py
fondat/asgi.py
fondat/cache.py
fondat/codec.py
fondat/context.py
fondat/csv.py
fondat/data.py
fondat/error.py
fondat/file.py
fondat/http.py
fondat/lazy.py
fondat/memory.py
fondat/monitor.py
fondat/oauth.py
fondat/openapi.py
fondat/pagination.py
fondat/patch.py
fondat/resource.py
fondat/security.py
fondat/sql.py
fondat/sqlite.py
fondat/stream.py
fondat/string.py
fondat/types.py
fondat/validation.py
fondat-4.2.0.dist-info/LICENSE
fondat-4.2.0.dist-info/METADATA
fondat-4.2.0.dist-info/WHEEL
fondat-4.2.0.dist-info/RECORD
