Metadata-Version: 2.1
Name: fondat
Version: 4.2.0
Summary: A foundation for resource-oriented backend applications.
Home-page: https://github.com/fondat/fondat/
License: MIT
Keywords: asgi,foundation,resource,openapi
Author: fondat authors
Requires-Python: >=3.11,<4.0
Classifier: Development Status :: 5 - Production/Stable
Classifier: Intended Audience :: Developers
Classifier: License :: OSI Approved :: MIT License
Classifier: Programming Language :: Python :: 3
Classifier: Programming Language :: Python :: 3.11
Classifier: Programming Language :: Python :: 3.12
Classifier: Topic :: Software Development :: Libraries :: Application Frameworks
Requires-Dist: aiosqlite (>=0.19,<0.20)
Requires-Dist: iso8601 (>=2.0,<3.0)
Requires-Dist: multidict (>=6.0,<7.0)
Requires-Dist: wrapt (>=1.16,<2.0)
Project-URL: Documentation, https://github.com/fondat/fondat/tree/main/docs
